autollm/__init__.py
autollm/auto/__init__.py
autollm/auto/embedding.py
autollm/auto/fastapi_app.py
autollm/auto/llm.py
autollm/auto/query_engine.py
autollm/auto/service_context.py
autollm/auto/vector_store_index.py
autollm/callbacks/__init__.py
autollm/callbacks/cost_calculating.py
autollm/serve/__init__.py
autollm/serve/docs.py
autollm/serve/utils.py
autollm/utils/__init__.py
autollm/utils/constants.py
autollm/utils/db_utils.py
autollm/utils/document_reading.py
autollm/utils/env_utils.py
autollm/utils/git_utils.py
autollm/utils/hash_utils.py
autollm/utils/lancedb_vectorstore.py
autollm/utils/llm_utils.py
autollm/utils/logging.py
autollm/utils/markdown_reader.py
autollm/utils/pdf_reader.py
autollm/utils/templates.py
autollm/utils/webpage_reader.py
autollm/utils/website_reader.py
autollm-0.1.10.dist-info/LICENSE
autollm-0.1.10.dist-info/METADATA
autollm-0.1.10.dist-info/WHEEL
autollm-0.1.10.dist-info/top_level.txt
autollm-0.1.10.dist-info/RECORD
