Metadata-Version: 2.1
Name: autollm
Version: 0.1.10
Summary: Ship RAG based LLM Web API's, in seconds.
Home-page: https://github.com/safevideo/autollm
Author: safevideo
Author-email: support@safevideo.ai
License: AGPL-3.0
Classifier: Intended Audience :: Developers
Classifier: Intended Audience :: Information Technology
Classifier: Intended Audience :: Science/Research
Classifier: License :: OSI Approved :: GNU Affero General Public License v3
Classifier: Operating System :: MacOS :: MacOS X
Classifier: Operating System :: Microsoft :: Windows
Classifier: Operating System :: POSIX
Classifier: Programming Language :: Python :: 3.8
Classifier: Programming Language :: Python :: 3.9
Classifier: Programming Language :: Python :: 3.10
Classifier: Programming Language :: Python :: 3.11
Classifier: Topic :: Software Development
Classifier: Topic :: Software Development :: Libraries
Classifier: Topic :: Software Development :: Libraries :: Python Modules
Classifier: Topic :: Scientific/Engineering :: Artificial Intelligence
Classifier: Topic :: Internet :: WWW/HTTP :: HTTP Servers
Requires-Python: >=3.8
License-File: LICENSE
Requires-Dist: llama-index ==0.9.27
Requires-Dist: litellm ==1.16.21
Requires-Dist: uvicorn
Requires-Dist: fastapi
Requires-Dist: python-dotenv
Requires-Dist: httpx
Requires-Dist: lancedb ==0.3.4
Provides-Extra: dev
Requires-Dist: pre-commit ==3.4.0 ; extra == 'dev'
Requires-Dist: pytest ==7.4.2 ; extra == 'dev'
Provides-Extra: readers
Requires-Dist: beautifulsoup4 ==4.12.2 ; extra == 'readers'
Requires-Dist: pdfminer.six ==20221105 ; extra == 'readers'
Requires-Dist: gitpython ==3.1.41 ; extra == 'readers'
Requires-Dist: docx2txt ; extra == 'readers'
Requires-Dist: EbookLib ; extra == 'readers'
Requires-Dist: html2text ; extra == 'readers'
Requires-Dist: nbconvert ; extra == 'readers'
Requires-Dist: langchain ; extra == 'readers'
